bard/__init__.py
bard/_version.py
bard/app.py
bard/audio.py
bard/html.py
bard/input.py
bard/install_desktop.py
bard/models.py
bard/util.py
bard/frontends/abstract.py
bard/frontends/terminal.py
bard/frontends/trayicon.py
bard_data/share/icon.png
bard_data/templates/bard.desktop
bard_cli-0.11.3.dist-info/LICENSE
bard_cli-0.11.3.dist-info/METADATA
bard_cli-0.11.3.dist-info/WHEEL
bard_cli-0.11.3.dist-info/entry_points.txt
bard_cli-0.11.3.dist-info/top_level.txt
bard_cli-0.11.3.dist-info/RECORD
