Metadata-Version: 2.2
Name: bard-cli
Version: 0.11.3
Summary: bard is a text to speech tool based on existing open-source models (local install) and APIs to install on your desktop
Author-email: Mahé Perrette <mahe.perrette@gmail.com>
License: MIT License
Project-URL: Homepage, https://github.com/perrette/bard
Keywords: text-to-speech,AI,language,openai
Classifier: Programming Language :: Python :: 3.9
Classifier: Programming Language :: Python :: 3.10
Classifier: Programming Language :: Python :: 3.11
Classifier: Programming Language :: Python :: 3.12
Classifier: Programming Language :: Python :: 3.13
Classifier: Operating System :: OS Independent
Requires-Python: >=3.9
License-File: LICENSE
Requires-Dist: numpy
Requires-Dist: sounddevice
Requires-Dist: soundfile
Requires-Dist: tqdm
Requires-Dist: pyperclip
Requires-Dist: pystray
Provides-Extra: app
Requires-Dist: PyGObject; extra == "app"
Provides-Extra: openai
Requires-Dist: openai; extra == "openai"
Provides-Extra: html
Requires-Dist: beautifulsoup4; extra == "html"
Requires-Dist: requests; extra == "html"
Requires-Dist: lxml_html_clean; extra == "html"
Requires-Dist: readability-lxml; extra == "html"
Provides-Extra: all
Requires-Dist: openai; extra == "all"
Requires-Dist: beautifulsoup4; extra == "all"
Requires-Dist: requests; extra == "all"
Requires-Dist: lxml_html_clean; extra == "all"
Requires-Dist: readability-lxml; extra == "all"
